sphinx_collapsible_autodoc/__init__.py
sphinx_collapsible_autodoc/_version.py
sphinx_collapsible_autodoc-0.0.1.dist-info/LICENSE
sphinx_collapsible_autodoc-0.0.1.dist-info/METADATA
sphinx_collapsible_autodoc-0.0.1.dist-info/WHEEL
sphinx_collapsible_autodoc-0.0.1.dist-info/top_level.txt
sphinx_collapsible_autodoc-0.0.1.dist-info/RECORD
